bbq/__init__.py
bbq/map_elites.py
bbq/utils.py
bbq/archives/__init__.py
bbq/archives/_archive_base.py
bbq/archives/_init_archive.py
bbq/domains/__init__.py
bbq/domains/_domain.py
bbq/domains/_parallel.py
bbq/emitters/__init__.py
bbq/emitters/_cma_es.py
bbq/emitters/_emitter_base.py
bbq/emitters/_init_emitter.py
bbq/emitters/_standard_emitters.py
bbq/logging/__init__.py
bbq/logging/logger.py
bbq/logging/plotting.py
bbq/logging/result_vis.py
bbq/logging/vis.py
bbq-0.2.0.dist-info/LICENSE
bbq-0.2.0.dist-info/METADATA
bbq-0.2.0.dist-info/WHEEL
bbq-0.2.0.dist-info/top_level.txt
bbq-0.2.0.dist-info/RECORD
