Metadata-Version: 2.1
Name: bbq
Version: 0.2.0
Summary: Tasty front end for PyRibs.
Home-page: https://github.com/agaier/bbq
Author: Adam Gaier
License-File: LICENSE
Requires-Dist: ribs (==0.4.0)
Requires-Dist: dask (>=2.0.0)
Requires-Dist: distributed (>=2.0.0)
Requires-Dist: fire (>=0.4.0)
Requires-Dist: humanfriendly (>=10.0)
Requires-Dist: numpy (>=1.17.0)
Requires-Dist: matplotlib (>=3.0.0)
